py_remote_recorder/__init__.py
py_remote_recorder/__main__.py
py_remote_recorder/backend/__init__.py
py_remote_recorder/backend/audio_record_functions.py
py_remote_recorder/backend/call_apis.py
py_remote_recorder/backend/record_functions.py
py_remote_recorder/backend/video_record_functions.py
py_remote_recorder/utils.py
py_remote_recorder-0.0.10.dist-info/LICENSE
py_remote_recorder-0.0.10.dist-info/METADATA
py_remote_recorder-0.0.10.dist-info/WHEEL
py_remote_recorder-0.0.10.dist-info/entry_points.txt
py_remote_recorder-0.0.10.dist-info/RECORD
