Metadata-Version: 2.1
Name: py_remote_recorder
Version: 0.0.10
Summary: 
Author: KlajdiBeqiraj
Author-email: k.beqiraj@myw.ai
Requires-Python: >=3.10,<4.0
Classifier: Programming Language :: Python :: 3
Classifier: Programming Language :: Python :: 3.10
Classifier: Programming Language :: Python :: 3.11
Classifier: Programming Language :: Python :: 3.12
Requires-Dist: fastapi (>=0.103.0)
Requires-Dist: mss (>=9.0.2,<10.0.0)
Requires-Dist: opencv-python (>=4.10.0.84,<5.0.0.0)
Requires-Dist: pre-commit (>=3.8.0,<4.0.0)
Requires-Dist: pyaudio (>=0.2.14,<0.3.0)
Requires-Dist: pyautogui (>=0.9.54,<0.10.0)
Requires-Dist: pydantic (>=2.8.2,<3.0.0)
Requires-Dist: pyngrok (>=7.2.0,<8.0.0)
Requires-Dist: screeninfo (>=0.8.1,<0.9.0)
Requires-Dist: uvicorn (>=0.30.6,<0.31.0)
